setup.py
bsst/__init__.py
bsst.egg-info/PKG-INFO
bsst.egg-info/SOURCES.txt
bsst.egg-info/dependency_links.txt
bsst-info/top_level.txt