Metadata-Version: 2.1
Name: bsst
Version: 15.2.2
Summary: Security research package
Home-page: UNKNOWN
Author: whybee
Author-email: whybee@wearehackerone.com
License: UNKNOWN
Platform: UNKNOWN
Classifier: Programming Language :: Python :: 3
Classifier: Programming Language :: Python :: 2
